README.md
setup.py
yliueTools/Color.py
yliueTools/Debug.py
yliueTools/__init__.py
yliueTools.egg-info/PKG-INFO
yliueTools.egg-info/SOURCES.txt
yliueTools.egg-info/dependency_links.txt
yliueTools.egg-info/top_level.txt
yliuetools.egg-info/PKG-INFO
yliuetools.egg-info/SOURCES.txt
yliuetools.egg-info/dependency_links.txt
yliuetools.egg-info/top_level.txt