Metadata-Version: 2.1
Name: yliuetools
Version: 1.0.5
Summary: 做的一些工具包
Author: yLIue
Author-email: 2138347243@qq.com
Keywords: python
Classifier: Programming Language :: Python :: 3.11
Classifier: Operating System :: Microsoft :: Windows
